crseg/__init__.py
crseg/cmd.py
crseg/crossroad.py
crseg/crossroad_connections.py
crseg/lane_description.py
crseg/link.py
crseg/region.py
crseg/regionfactory.py
crseg/reliability.py
crseg/segmentation.py
crseg/utils.py
crossroads_segmentation-0.1.20.dist-info/METADATA
crossroads_segmentation-0.1.20.dist-info/WHEEL
crossroads_segmentation-0.1.20.dist-info/entry_points.txt
crossroads_segmentation-0.1.20.dist-info/top_level.txt
crossroads_segmentation-0.1.20.dist-info/RECORD
