Metadata-Version: 2.1
Name: crossroads-segmentation
Version: 0.1.20
Summary: Crossroads segmentation is a python tool that produces automatic segmentations of data from OpenStreetMap.
Home-page: https://github.com/jmtrivial/crossroads-segmentation/
Author: Jean-Marie Favreau
Author-email: j-marie.favreau@uca.fr
License: AGPL-3.0
Classifier: License :: OSI Approved :: GNU Affero General Public License v3 or later (AGPLv3+)
Classifier: Programming Language :: Python :: 3
Classifier: Programming Language :: Python :: 3.7
